LICENSE.txt
MANIFEST.in
README.rst
setup.py
TBGXMLUtils.egg-info/PKG-INFO
TBGXMLUtils.egg-info/SOURCES.txt
TBGXMLUtils.egg-info/dependency_links.txt
TBGXMLUtils.egg-info/requires.txt
TBGXMLUtils.egg-info/top_level.txt
tbgxmlutils/__init__.py
tbgxmlutils/readme.py
tbgxmlutils/xmlutils.py