Metadata-Version: 1.0
Name: TBGXMLUtils
Version: 0.1.3
Summary: Easy XML utility.
Home-page: http://github.com/Schwarzschild/TBGXMLUtils
Author: Marc Schwarzschild
Author-email: ms@TheBrookhavenGroup.com
License: MIT
Keywords: xml
Platform: UNKNOWN
